TableGenerator/CreatePDFTable.py
TableGenerator/Degenerator.py
TableGenerator/GenerateTableData.py
TableGenerator/Options.py
TableGenerator/__init__.py
TableGenerator/example_create_img.py
TableGenerator/example_create_pdf.py
TableGenerator/fonts/FreeMono.ttf
TableGenerator/fonts/FreeMonoBold.ttf
TableGenerator/fonts/FreeSans.ttf
TableGenerator/fonts/FreeSansBold.ttf
extractable-1.0.2.dist-info/METADATA
extractable-1.0.2.dist-info/WHEEL
extractable-1.0.2.dist-info/licenses/LICENSE.txt
extractable/.idea/.gitignore
extractable/.idea/Extractable.iml
extractable/.idea/inspectionProfiles/profiles_settings.xml
extractable/.idea/misc.xml
extractable/.idea/modules.xml
extractable/Dataobj.py
extractable/Datatypes/Bbox.py
extractable/Datatypes/Cell.py
extractable/Datatypes/Row.py
extractable/Datatypes/Table.py
extractable/Extractor.py
extractable/Filetype.py
extractable/ImagePreprocessor.py
extractable/Logger.py
extractable/ModeManager.py
extractable/PDFtoImageConvertor.py
extractable/Pipe.py
extractable/StructureDetector.py
extractable/TableDetector.py
extractable/TextExtractor.py
extractable/__init__.py
fpdf/__init__.py
fpdf/actions.py
fpdf/annotations.py
fpdf/deprecation.py
fpdf/drawing.py
fpdf/encryption.py
fpdf/enums.py
fpdf/errors.py
fpdf/fonts.py
fpdf/fpdf.py
fpdf/graphics_state.py
fpdf/html.py
fpdf/image_parsing.py
fpdf/line_break.py
fpdf/linearization.py
fpdf/outline.py
fpdf/output.py
fpdf/prefs.py
fpdf/recorder.py
fpdf/sign.py
fpdf/structure_tree.py
fpdf/svg.py
fpdf/syntax.py
fpdf/table.py
fpdf/template.py
fpdf/transitions.py
fpdf/util.py
extractable-1.0.2.dist-info/RECORD
