Metadata-Version: 2.1
Name: extractable
Version: 1.0.2
Summary: Extract tables from PDFs
Keywords: python,table-extraction,pdf,TATR,Table Transformer,Computer Vision
Author-Email: "Suleymen C. Kandrouch" <suleyleeuw@gmail.com>
License: MIT
Classifier: License :: OSI Approved :: MIT License
Classifier: Natural Language :: English
Classifier: Programming Language :: Python :: 3
Classifier: Programming Language :: Python :: 3.11
Project-URL: Homepage, https://github.com/SuleyNL/Extractable
Project-URL: Downloads, https://github.com/SuleyNL/Extractable/archive/refs/tags/v1.0.0.tar.gz
Requires-Python: <3.12,>=3.9
Requires-Dist: Faker~=18.9.0
Requires-Dist: Pillow>=9.2.0
Requires-Dist: PyPDF2~=3.0.1
Requires-Dist: build~=0.10.0
Requires-Dist: defusedxml~=0.7.1
Requires-Dist: matplotlib>=3
Requires-Dist: mkdocs~=1.4.3
Requires-Dist: openpyxl~=3.1.2
Requires-Dist: pandas~=2.0.2
Requires-Dist: pandas-stubs~=2.0.2.230605
Requires-Dist: pdf2image~=1.15.1
Requires-Dist: pdf2jpg~=1.1
Requires-Dist: pytesseract~=0.3.10
Requires-Dist: pytest>=7.3.1
Requires-Dist: scipy~=1.10.1
Requires-Dist: setuptools>=61.0
Requires-Dist: svgwrite~=1.4.3
Requires-Dist: timm~=0.9.2
Requires-Dist: toolz~=0.12.0
Requires-Dist: torch~=2.1.0
Requires-Dist: transformers~=4.29.2
Requires-Dist: wheel~=0.40.0
Requires-Dist: bs4>=0.0.1
Requires-Dist: requests>=2.31.0
Requires-Dist: PyCryptodome>=3.18.0
Requires-Dist: pytest>=7.4.2; extra == "dev"
Requires-Dist: pdm>=2.7.0; extra == "dev"
Provides-Extra: dev
